{"line": 266, "tri": [{"h": "an unofficial designation", "r": "relate", "t": "Indian language films", "c": 0.05754878371953964}, {"h": "the Indian film trade", "r": "relate", "t": "Indian language films", "c": 0.05911531671881676}, {"h": "the media", "r": "relate", "t": "Indian language films", "c": 0.0772719755768776}, {"h": "the media", "r": "relate", "t": "10 billion Indian rupees", "c": 0.05445544049143791}, {"h": "the media", "r": "relate", "t": "India", "c": 0.054682500660419464}, {"h": "Indian language films", "r": "crore", "t": "10 billion Indian rupees", "c": 0.05563780665397644}, {"h": "The Conclusion", "r": "become", "t": "the first Indian film", "c": 0.0897851288318634}, {"h": "The 1000 crore club", "r": "precede", "t": "the 100 crore club", "c": 0.09928162023425102}]}
