{"line": 483, "tri": [{"h": "more recent 2009 - 2010 data", "r": "among", "t": "the top four states", "c": 0.07946443930268288}, {"h": "more recent 2009 - 2010 data", "r": "show", "t": "Florida", "c": 0.10269729793071747}, {"h": "Florida", "r": "among", "t": "the top four states", "c": 0.08375514671206474}, {"h": "more recent 2009 - 2010 data", "r": "show", "t": "the top four states", "c": 0.06814096122980118}, {"h": "more recent 2009 - 2010 data", "r": "no", "t": "Florida", "c": 0.061971891671419144}, {"h": "more recent 2009 - 2010 data", "r": "no", "t": "the top four states", "c": 0.06041466072201729}, {"h": "Production activity", "r": "concentrate", "t": "South Florida", "c": 0.0960895624011755}, {"h": "Production activity", "r": "concentrate", "t": "two regions", "c": 0.119277223944664}, {"h": "Production activity", "r": "concentrate", "t": "Central Florida", "c": 0.09145041927695274}, {"h": "Production activity", "r": "concentrate", "t": "( Orlando", "c": 0.09420742839574814}, {"h": "Production activity", "r": "concentrate", "t": "Tampa", "c": 0.09277633391320705}, {"h": "large projects", "r": "like", "t": "Neal Moritz 's 2 Fast 2 Furious", "c": 0.05298873968422413}, {"h": "large projects", "r": "like", "t": "Jerry Bruckheimer 's Bad Boys film series", "c": 0.060401551425457}, {"h": "The Central Florida area", "r": "star", "t": "John Travolta", "c": 0.05211063660681248}, {"h": "The Central Florida area", "r": "feature", "t": "The Punisher", "c": 0.058599986135959625}, {"h": "The Central Florida area", "r": "feature", "t": "John Travolta", "c": 0.05277885124087334}, {"h": "The state", "r": "thank", "t": "moderate climate", "c": 0.07698112353682518}, {"h": "The state", "r": "thank", "t": "Florida year - round sunshine", "c": 0.0800708457827568}, {"h": "Florida", "r": "thank", "t": "Florida year - round sunshine", "c": 0.055396918207407}, {"h": "Florida", "r": "thank", "t": "moderate climate", "c": 0.05230719596147537}, {"h": "a long film history", "r": "thank", "t": "Florida year - round sunshine", "c": 0.08884863555431366}, {"h": "a long film history", "r": "thank", "t": "moderate climate", "c": 0.08575891330838203}, {"h": "Film classics", "r": "throughout", "t": "Florida", "c": 0.07559872977435589}, {"h": "Film classics", "r": "film", "t": "Moon", "c": 0.10315221175551414}, {"h": "Film classics", "r": "film", "t": "Miami", "c": 0.10274207964539528}, {"h": "Film classics", "r": "film", "t": "Florida", "c": 0.10755537450313568}, {"h": "Film classics", "r": "throughout", "t": "Miami", "c": 0.055562037974596024}, {"h": "Film classics", "r": "throughout", "t": "Moon", "c": 0.05513387732207775}, {"h": "the early 1990s", "r": "experience", "t": "film production", "c": 0.1102374792098999}, {"h": "Orlando", "r": "experience", "t": "film production", "c": 0.10223852470517159}, {"h": "the early 1990s", "r": "experience", "t": "a great boom", "c": 0.13354100659489632}, {"h": "Orlando", "r": "experience", "t": "a great boom", "c": 0.125542052090168}, {"h": "The construction", "r": "attract", "t": "Orlando", "c": 0.05983686447143555}, {"h": "The construction", "r": "attract", "t": "many filmmakers", "c": 0.07098934054374695}, {"h": "the Disney - MGM Studios", "r": "attract", "t": "many filmmakers", "c": 0.060401368886232376}, {"h": "Universal Studios production facilities", "r": "attract", "t": "many filmmakers", "c": 0.0780855119228363}, {"h": "Universal Studios production facilities", "r": "attract", "t": "Orlando", "c": 0.0669330358505249}, {"h": "Films", "r": "lead", "t": "the pack", "c": 0.07550070248544216}, {"h": "Ron Howard 's Parenthood", "r": "lead", "t": "the pack", "c": 0.07323675230145454}, {"h": "syndicated television shows", "r": "lead", "t": "the pack", "c": 0.07809079624712467}, {"h": "The Adventures", "r": "lead", "t": "the pack", "c": 0.08203497715294361}, {"h": "Superboy", "r": "lead", "t": "the pack", "c": 0.07682289555668831}, {"h": "the Steven Spielberg series", "r": "seaQuest", "t": "DSV", "c": 0.06608773395419121}, {"h": "the Steven Spielberg series", "r": "seaQuest", "t": "the Earth", "c": 0.05118682235479355}, {"h": "the Steven Spielberg series", "r": "seaQuest", "t": "Tom Hank", "c": 0.0527731217443943}, {"h": "the early 1990s", "r": "acquire", "t": "Orlando surging film industry", "c": 0.09609358385205269}, {"h": "Orlando", "r": "acquire", "t": "the nickname", "c": 0.12519782781600952}, {"h": "the early 1990s", "r": "acquire", "t": "the nickname", "c": 0.1353304535150528}, {"h": "Orlando", "r": "acquire", "t": "Orlando surging film industry", "c": 0.08596095815300941}, {"h": "the early 1990s", "r": "acquire", "t": "Hollywood East", "c": 0.09165187366306782}, {"h": "Orlando", "r": "acquire", "t": "Hollywood East", "c": 0.08151924796402454}, {"h": "film production", "r": "appear", "t": "Florida", "c": 0.06654321402311325}, {"h": "film production", "r": "appear", "t": "the decline", "c": 0.0750950276851654}, {"h": "film production", "r": "appear", "t": "another boom", "c": 0.060322219505906105}, {"h": "film production", "r": "appear", "t": "the phenomenal success", "c": 0.07462221384048462}, {"h": "film production", "r": "appear", "t": "1998 's The Blair Witch Project", "c": 0.06280729919672012}, {"h": "film production", "r": "lead", "t": "another boom", "c": 0.06062816269695759}, {"h": "the decline", "r": "lead", "t": "another boom", "c": 0.05732825957238674}, {"h": "the phenomenal success", "r": "lead", "t": "another boom", "c": 0.058837926015257835}, {"h": "Florida", "r": "lead", "t": "another boom", "c": 0.05324284918606281}, {"h": "1998 's The Blair Witch Project", "r": "lead", "t": "another boom", "c": 0.06569805927574635}, {"h": "1998 's The Blair Witch Project", "r": "film", "t": "1998 's The Blair Witch Project director", "c": 0.05577579513192177}, {"h": "1998 's The Blair Witch Project", "r": "film", "t": "entire crew", "c": 0.05757681466639042}, {"h": "1998 's The Blair Witch Project", "r": "film", "t": "Maryland", "c": 0.06149199604988098}, {"h": "1998 's The Blair Witch Project", "r": "film", "t": "film school graduates", "c": 0.06515616923570633}, {"h": "1998 's The Blair Witch Project", "r": "lead", "t": "Florida", "c": 0.06383747607469559}, {"h": "1998 's The Blair Witch Project", "r": "lead", "t": "a new wave", "c": 0.06923019140958786}, {"h": "1998 's The Blair Witch Project", "r": "lead", "t": "film production", "c": 0.08330019190907478}]}
