{"line": 152, "tri": [{"h": "a written work", "r": "publish", "t": "a print or electronic medium", "c": 0.13480260223150253}, {"h": "An article", "r": "publish", "t": "a print or electronic medium", "c": 0.1267276629805565}, {"h": "", "r": "may", "t": "", "c": 0.07732401415705681}, {"h": "An article", "r": "propagate", "t": "news", "c": 0.06451445259153843}, {"h": "An article", "r": "research", "t": "academic analysis", "c": 0.05276026763021946}, {"h": "An article", "r": "result", "t": "academic analysis", "c": 0.05408277548849583}, {"h": "An article", "r": "result", "t": "debate", "c": 0.050031766295433044}, {"h": "An article", "r": "research", "t": "debate", "c": 0.050598401576280594}, {"h": "the purpose", "r": "propagate", "t": "academic analysis", "c": 0.052283743396401405}, {"h": "the purpose", "r": "research", "t": "academic analysis", "c": 0.05535697378218174}, {"h": "the purpose", "r": "propagate", "t": "news", "c": 0.06777756288647652}, {"h": "the purpose", "r": "research", "t": "debate", "c": 0.053195107728242874}, {"h": "news", "r": "result", "t": "academic analysis", "c": 0.07356409914791584}, {"h": "news", "r": "research", "t": "academic analysis", "c": 0.07052330859005451}, {"h": "news", "r": "research", "t": "debate", "c": 0.06836144253611565}, {"h": "news", "r": "result", "t": "debate", "c": 0.06951308995485306}, {"h": "A news article", "r": "discusse", "t": "a specific topic", "c": 0.08164598047733307}, {"h": "A news article", "r": "discusse", "t": "current or recent news", "c": 0.0958123616874218}, {"h": "A news article", "r": "discusse", "t": "club newsletters", "c": 0.07988659851253033}, {"h": "A news article", "r": "discusse", "t": "( i.e. daily newspapers", "c": 0.0766037730500102}, {"h": "A news article", "r": "discusse", "t": "technology news websites", "c": 0.07710899692028761}, {"h": "A news article", "r": "discusse", "t": "i.e. political or trade news magazines", "c": 0.07329640816897154}, {"h": "A news article", "r": "discusse", "t": "either general interest", "c": 0.08463635481894016}, {"h": "A news article", "r": "contain", "t": "accounts", "c": 0.08750997111201286}, {"h": "A news article", "r": "contain", "t": "photographs", "c": 0.13754836842417717}, {"h": "A news article", "r": "contain", "t": "graphs", "c": 0.10577210411429405}, {"h": "A news article", "r": "contain", "t": "polls", "c": 0.050075776875019073}, {"h": "A news article", "r": "contain", "t": "recollections", "c": 0.0505728330463171}, {"h": "A news article", "r": "contain", "t": "debates", "c": 0.0587284080684185}, {"h": "A news article", "r": "contain", "t": "statistics", "c": 0.052498701959848404}, {"h": "A news article", "r": "contain", "t": "interviews", "c": 0.08656544610857964}, {"h": "A news article", "r": "contain", "t": "the topic", "c": 0.07624039053916931}, {"h": "Headlines", "r": "focus", "t": "the reader 's attention", "c": 0.07782890647649765}, {"h": "Headlines", "r": "focus", "t": "a particular ( or main ) part", "c": 0.06072569265961647}, {"h": "Headlines", "r": "use", "t": "the reader 's attention", "c": 0.06929083168506622}, {"h": "Headlines", "r": "use", "t": "a particular ( or main ) part", "c": 0.05811745300889015}, {"h": "Headlines", "r": "focus", "t": "A news article", "c": 0.0709669478237629}, {"h": "Headlines", "r": "use", "t": "A news article", "c": 0.05765644274652004}, {"h": "The writer", "r": "give", "t": "facts", "c": 0.15336261689662933}, {"h": "The writer", "r": "give", "t": "answers", "c": 0.0850081667304039}, {"h": "The writer", "r": "give", "t": "general questions", "c": 0.079377681016922}, {"h": "The writer", "r": "give", "t": "detailed information", "c": 0.10880935937166214}, {"h": "References", "r": "confirm", "t": "the factuality", "c": 0.050909679383039474}, {"h": "people", "r": "confirm", "t": "the factuality", "c": 0.06512303464114666}, {"h": "people", "r": "confirm", "t": "the reliability", "c": 0.05789325386285782}, {"h": "people", "r": "confirm", "t": "the writer 's information", "c": 0.05088444147258997}, {"h": "people", "r": "confirm", "t": "The writer source", "c": 0.057380661368370056}, {"h": "the written accounts", "r": "confirm", "t": "the factuality", "c": 0.07521731965243816}, {"h": "the written accounts", "r": "confirm", "t": "the writer 's information", "c": 0.060978726483881474}, {"h": "the written accounts", "r": "confirm", "t": "The writer source", "c": 0.06747494637966156}, {"h": "interviews", "r": "confirm", "t": "the factuality", "c": 0.09243449755012989}, {"h": "the written accounts", "r": "confirm", "t": "the reliability", "c": 0.06798753887414932}, {"h": "interviews", "r": "confirm", "t": "the reliability", "c": 0.08520471677184105}, {"h": "interviews", "r": "confirm", "t": "The writer source", "c": 0.08469212427735329}, {"h": "debates", "r": "confirm", "t": "the writer 's information", "c": 0.061945159919559956}, {"h": "debates", "r": "confirm", "t": "the factuality", "c": 0.07618375308811665}, {"h": "debates", "r": "confirm", "t": "the reliability", "c": 0.0689539723098278}, {"h": "interviews", "r": "confirm", "t": "the writer 's information", "c": 0.0781959043815732}, {"h": "debates", "r": "confirm", "t": "The writer source", "c": 0.06844137981534004}, {"h": "The writer", "r": "ensure", "t": "the reader", "c": 0.06590516492724419}, {"h": "The writer", "r": "read", "t": "A news article", "c": 0.08504225313663483}, {"h": "The writer", "r": "use", "t": "redirection", "c": 0.08978942409157753}, {"h": "The writer", "r": "use", "t": "A news article", "c": 0.07724867574870586}, {"h": "The writer", "r": "keep", "t": "A news article", "c": 0.07493747770786285}, {"h": "The writer", "r": "use", "t": "the reader attention", "c": 0.07609940692782402}, {"h": "The writer", "r": "use", "t": "the reader", "c": 0.09038599207997322}, {"h": "The writer", "r": "keep", "t": "the reader attention", "c": 0.06328072398900986}, {"h": "The writer", "r": "use", "t": "other articles", "c": 0.08423245325684547}, {"h": "The writer", "r": "read", "t": "other articles", "c": 0.06584519147872925}, {"h": "The writer", "r": "read", "t": "the reader attention", "c": 0.051799310371279716}, {"h": "redirection", "r": "ensure", "t": "the reader", "c": 0.07697948068380356}, {"h": "redirection", "r": "read", "t": "A news article", "c": 0.08193516358733177}, {"h": "The writer", "r": "ensure", "t": "A news article", "c": 0.05208930931985378}, {"h": "The writer", "r": "keep", "t": "other articles", "c": 0.06001234985888004}, {"h": "redirection", "r": "keep", "t": "A news article", "c": 0.0652508195489645}, {"h": "redirection", "r": "ensure", "t": "the reader attention", "c": 0.05911950394511223}, {"h": "redirection", "r": "keep", "t": "the reader attention", "c": 0.053594065830111504}, {"h": "redirection", "r": "draw", "t": "the reader attention", "c": 0.051080670207738876}, {"h": "redirection", "r": "ensure", "t": "A news article", "c": 0.06316362507641315}, {"h": "redirection", "r": "ensure", "t": "other articles", "c": 0.0607304722070694}, {"h": "redirection", "r": "keep", "t": "other articles", "c": 0.05032569169998169}, {"h": "the reader", "r": "keep", "t": "the reader attention", "c": 0.07084828987717628}, {"h": "the reader", "r": "keep", "t": "A news article", "c": 0.08250504359602928}, {"h": "redirection", "r": "read", "t": "other articles", "c": 0.0627381019294262}, {"h": "the reader", "r": "read", "t": "the reader attention", "c": 0.05681009404361248}, {"h": "the reader", "r": "read", "t": "other articles", "c": 0.07085597515106201}, {"h": "the reader", "r": "keep", "t": "other articles", "c": 0.06757991574704647}, {"h": "the reader", "r": "draw", "t": "other articles", "c": 0.05067597143352032}, {"h": "A news article", "r": "draw", "t": "the reader attention", "c": 0.05467167682945728}, {"h": "the reader", "r": "draw", "t": "the reader attention", "c": 0.0546030979603529}, {"h": "the reader", "r": "read", "t": "A news article", "c": 0.09005303680896759}, {"h": "A news article", "r": "draw", "t": "other articles", "c": 0.0507445503026247}, {"h": "example", "r": "like", "t": "page", "c": 0.07574740052223206}, {"h": "example", "r": "like", "t": "a page", "c": 0.06044747866690159}, {"h": "example", "r": "like", "t": "A news article", "c": 0.06380751170217991}, {"h": "example", "r": "like", "t": "the reader", "c": 0.06860686093568802}, {"h": "phrases", "r": "like", "t": "page", "c": 0.07132185623049736}, {"h": "phrases", "r": "like", "t": "the reader", "c": 0.06418131664395332}, {"h": "phrases", "r": "like", "t": "a page", "c": 0.05602193437516689}, {"h": "phrases", "r": "like", "t": "A news article", "c": 0.05938196741044521}, {"h": "newspaper reporters", "r": "train", "t": "inverted pyramid style", "c": 0.10567158088088036}, {"h": "newspaper reporters", "r": "write", "t": "the first paragraph", "c": 0.08644868433475494}, {"h": "newspaper reporters", "r": "write", "t": "all the most important information", "c": 0.08169057592749596}, {"h": "newspaper reporters", "r": "train", "t": "the first paragraph", "c": 0.06639265641570091}, {"h": "newspaper reporters", "r": "train", "t": "all the most important information", "c": 0.07095342688262463}, {"h": "newspaper reporters", "r": "write", "t": "inverted pyramid style", "c": 0.1062190905213356}, {"h": "the less vital details", "r": "push", "t": "the potentially destructive impact", "c": 0.07017790153622627}, {"h": "the less vital details", "r": "push", "t": "the story", "c": 0.05376932770013809}, {"h": "the less vital details", "r": "towards", "t": "the potentially destructive impact", "c": 0.061834242194890976}, {"h": "the less vital details", "r": "then", "t": "the potentially destructive impact", "c": 0.0577623825520277}, {"h": "the less vital details", "r": "push", "t": "the end", "c": 0.06238999217748642}, {"h": "the less vital details", "r": "towards", "t": "the end", "c": 0.07965096831321716}, {"h": "the less vital details", "r": "towards", "t": "the story", "c": 0.06112399883568287}, {"h": "the end", "r": "then", "t": "the potentially destructive impact", "c": 0.05985544063150883}, {"h": "the story", "r": "then", "t": "the potentially destructive impact", "c": 0.06154388561844826}, {"h": "A headline", "r": "above", "t": "a newspaper article", "c": 0.0782722719013691}, {"h": "A headline", "r": "indicate", "t": "a newspaper article", "c": 0.08984798938035965}, {"h": "text", "r": "above", "t": "a newspaper article", "c": 0.11201716586947441}, {"h": "text", "r": "indicate", "t": "a newspaper article", "c": 0.11387676000595093}]}
