{"line": 98, "tri": [{"h": "College circuit", "r": "show", "t": "college campuses", "c": 0.061521729454398155}, {"h": "a form", "r": "show", "t": "college campuses", "c": 0.06614330038428307}, {"h": "old films", "r": "show", "t": "college campuses", "c": 0.07255447655916214}, {"h": "motion picture distribution", "r": "show", "t": "college campuses", "c": 0.07034722715616226}, {"h": "new ones", "r": "show", "t": "college campuses", "c": 0.07366396114230156}, {"h": "The selections", "r": "range", "t": "art house fare", "c": 0.11738453805446625}, {"h": "The selections", "r": "range", "t": "cult classics", "c": 0.10023557394742966}, {"h": "The selections", "r": "see", "t": "midnight movies", "c": 0.08211882412433624}, {"h": "The selections", "r": "range", "t": "wide release films", "c": 0.10230861604213715}, {"h": "The selections", "r": "range", "t": "a similar practice", "c": 0.08034047484397888}, {"h": "art house fare", "r": "see", "t": "midnight movies", "c": 0.07847808580845594}, {"h": "The selections", "r": "range", "t": "midnight movies", "c": 0.09088581055402756}, {"h": "wide release films", "r": "see", "t": "midnight movies", "c": 0.0834319032728672}, {"h": "cult classics", "r": "see", "t": "a similar practice", "c": 0.0528747271746397}, {"h": "cult classics", "r": "see", "t": "midnight movies", "c": 0.088348887860775}, {"h": "the 1950s", "r": "teach", "t": "colleges", "c": 0.06634439341723919}, {"h": "60 's , classes", "r": "teach", "t": "colleges", "c": 0.0635289866477251}, {"h": "cinema theory", "r": "teach", "t": "colleges", "c": 0.06777126528322697}, {"h": "history", "r": "teach", "t": "colleges", "c": 0.06720748171210289}, {"h": "colleges", "r": "across", "t": "the United States", "c": 0.05124048329889774}, {"h": "the growing interest", "r": "screened", "t": "students", "c": 0.07953404262661934}, {"h": "the growing interest", "r": "screened", "t": "a reduced price", "c": 0.08392114192247391}, {"h": "film", "r": "screened", "t": "students", "c": 0.1514662355184555}, {"h": "film", "r": "screened", "t": "a reduced price", "c": 0.15585333481431007}, {"h": "prints", "r": "screened", "t": "a reduced price", "c": 0.1170986033976078}, {"h": "prints", "r": "screened", "t": "students", "c": 0.11271150410175323}, {"h": "Several movies", "r": "salvage", "t": "most notably Citizen Kane", "c": 0.0762450136244297}, {"h": "Several movies", "r": "salvage", "t": "screened", "c": 0.08522717282176018}, {"h": "Several movies", "r": "thank", "t": "screened", "c": 0.09825725108385086}, {"h": "Several movies", "r": "thank", "t": "most notably Citizen Kane", "c": 0.08023329451680183}, {"h": "the movies", "r": "throughout", "t": "the years", "c": 0.07556354627013206}, {"h": "the movies", "r": "throughout", "t": "specious artistic merit", "c": 0.05276340991258621}, {"h": "the movies", "r": "either", "t": "specious artistic merit", "c": 0.05072175711393356}, {"h": "the movies", "r": "controversial", "t": "specious artistic merit", "c": 0.06235063634812832}, {"h": "college circuits", "r": "throughout", "t": "specious artistic merit", "c": 0.06300364062190056}, {"h": "college circuits", "r": "controversial", "t": "specious artistic merit", "c": 0.06801658682525158}, {"h": "college circuits", "r": "either", "t": "specious artistic merit", "c": 0.05177948996424675}, {"h": "college circuits", "r": "throughout", "t": "the years", "c": 0.08580377697944641}, {"h": "the years", "r": "controversial", "t": "specious artistic merit", "c": 0.06763423047959805}, {"h": "the years", "r": "either", "t": "specious artistic merit", "c": 0.0593727882951498}, {"h": "The content", "r": "appeal", "t": "college - age sensibilities", "c": 0.06066385842859745}, {"h": "The content", "r": "throughout", "t": "the years", "c": 0.0819636657834053}, {"h": "The content", "r": "throughout", "t": "college - age sensibilities", "c": 0.059021977707743645}, {"h": "the movies", "r": "appeal", "t": "college - age sensibilities", "c": 0.058567121624946594}, {"h": "college circuits", "r": "throughout", "t": "college - age sensibilities", "c": 0.06027555279433727}, {"h": "the movies", "r": "throughout", "t": "college - age sensibilities", "c": 0.052490731701254845}, {"h": "college circuits", "r": "appeal", "t": "college - age sensibilities", "c": 0.07126455195248127}, {"h": "the years", "r": "appeal", "t": "college - age sensibilities", "c": 0.07564719952642918}, {"h": "Critics", "r": "express", "t": "suspicion", "c": 0.09547299705445766}, {"h": "Critics", "r": "therefore", "t": "become", "c": 0.05140485521405935}, {"h": "Roger Ebert", "r": "express", "t": "suspicion", "c": 0.0962430015206337}, {"h": "Roger Ebert", "r": "therefore", "t": "become", "c": 0.05036174599081278}, {"h": "suspicion", "r": "therefore", "t": "become", "c": 0.051552935503423214}, {"h": "exploitive material", "r": "therefore", "t": "become", "c": 0.050436437129974365}, {"h": "sex", "r": "therefore", "t": "become", "c": 0.05374213866889477}, {"h": "violence", "r": "therefore", "t": "become", "c": 0.05173072498291731}, {"h": "drug use", "r": "therefore", "t": "become", "c": 0.05296178814023733}, {"h": "means", "r": "therefore", "t": "become", "c": 0.05356991617009044}, {"h": "cinema studies", "r": "therefore", "t": "become", "c": 0.06033691018819809}, {"h": "a grindhouse film", "r": "therefore", "t": "become", "c": 0.06801898032426834}, {"h": "an argument", "r": "level", "t": "Ken Russell", "c": 0.10071590170264244}, {"h": "an argument", "r": "against", "t": "Blue Velvet", "c": 0.08743482083082199}, {"h": "an argument", "r": "against", "t": "Ken Russell", "c": 0.07492893747985363}, {"h": "an argument", "r": "level", "t": "Blue Velvet", "c": 0.1001792848110199}, {"h": "an argument", "r": "level", "t": "the ouvre", "c": 0.10213060490787029}, {"h": "an argument", "r": "against", "t": "the ouvre", "c": 0.08457887917757034}]}
